{
  "timestamp": "2025-11-10T16:07:21.176583",
  "input_folder": "results\\multi_format_all",
  "languages_processed": 9,
  "total_qa_pairs": 180,
  "total_edits_evaluated": 720,
  "approved_rate": 0.9888888888888889,
  "average_score": 7.022222222222222,
  "per_language": {
    "ar": {
      "qa_pairs": 20,
      "approved": 20,
      "approval_rate": 1.0,
      "average_score": 7.35,
      "total_edits_evaluated": 80
    },
    "bn": {
      "qa_pairs": 20,
      "approved": 20,
      "approval_rate": 1.0,
      "average_score": 7.15,
      "total_edits_evaluated": 80
    },
    "en": {
      "qa_pairs": 20,
      "approved": 20,
      "approval_rate": 1.0,
      "average_score": 8.1,
      "total_edits_evaluated": 80
    },
    "fi": {
      "qa_pairs": 20,
      "approved": 20,
      "approval_rate": 1.0,
      "average_score": 6.0,
      "total_edits_evaluated": 80
    },
    "id": {
      "qa_pairs": 20,
      "approved": 20,
      "approval_rate": 1.0,
      "average_score": 8.45,
      "total_edits_evaluated": 80
    },
    "ko": {
      "qa_pairs": 20,
      "approved": 18,
      "approval_rate": 0.9,
      "average_score": 6.2,
      "total_edits_evaluated": 80
    },
    "ru": {
      "qa_pairs": 20,
      "approved": 20,
      "approval_rate": 1.0,
      "average_score": 7.25,
      "total_edits_evaluated": 80
    },
    "sw": {
      "qa_pairs": 20,
      "approved": 20,
      "approval_rate": 1.0,
      "average_score": 5.65,
      "total_edits_evaluated": 80
    },
    "te": {
      "qa_pairs": 20,
      "approved": 20,
      "approval_rate": 1.0,
      "average_score": 7.05,
      "total_edits_evaluated": 80
    }
  }
}